mediamtx/__init__.py
mediamtx/mediamtx.py
mediamtx_py-0.0.4.dist-info/licenses/LICENSE
mediamtx_yt/__init__.py
mediamtx_yt/mediamtx.py
mediamtx_yt-koike/__init__.py
mediamtx_yt-koike/mediamtx.py
mediamtx_py-0.0.4.dist-info/METADATA
mediamtx_py-0.0.4.dist-info/WHEEL
mediamtx_py-0.0.4.dist-info/top_level.txt
mediamtx_py-0.0.4.dist-info/RECORD
