Metadata-Version: 2.4
Name: mediamtx-py
Version: 0.0.4
Summary: Unofficial Python wrapper of MediaMTX
Author-email: yt-koike <y.koike.2001code@gmail.com>
License-Expression: MIT
Project-URL: Repository, https://github.com/yt-koike/MediaMTX-py
Classifier: Programming Language :: Python :: 3
Classifier: Operating System :: Microsoft :: Windows :: Windows 11
Classifier: Operating System :: POSIX :: Linux
Requires-Python: >=3.9
License-File: LICENSE
Requires-Dist: PyYAML==6.0.2
Requires-Dist: requests==2.32.5
Dynamic: license-file
